sqlfluff_py/__init__.py
sqlfluff_py/__main__.py
sqlfluff_py/fix.py
sqlfluff_py/py.typed
sqlfluff_py/tokenize.py
sqlfluff_py/typing.py
sqlfluff_py/utils.py
sqlfluff_py-1.0.0a1.dist-info/licenses/LICENSE
sqlfluff_py-1.0.0a1.dist-info/METADATA
sqlfluff_py-1.0.0a1.dist-info/WHEEL
sqlfluff_py-1.0.0a1.dist-info/entry_points.txt
sqlfluff_py-1.0.0a1.dist-info/top_level.txt
sqlfluff_py-1.0.0a1.dist-info/RECORD
