Metadata-Version: 2.4
Name: sqlfluff-py
Version: 1.0.0a1
Summary: SQLFluff for python script
License: MIT License
Keywords: sqlfluff,sql,linter,formatter
Classifier: Development Status :: 3 - Alpha
Classifier: Environment :: Console
Classifier: Intended Audience :: Developers
Classifier: License :: OSI Approved :: MIT License
Classifier: Operating System :: Unix
Classifier: Operating System :: POSIX
Classifier: Operating System :: MacOS
Classifier: Operating System :: Microsoft :: Windows
Classifier: Programming Language :: Python
Classifier: Programming Language :: Python :: 3
Classifier: Programming Language :: Python :: 3.9
Classifier: Programming Language :: Python :: 3.10
Classifier: Programming Language :: Python :: 3.11
Classifier: Programming Language :: Python :: 3.12
Classifier: Programming Language :: Python :: 3.13
Classifier: Programming Language :: Python :: Implementation :: CPython
Classifier: Programming Language :: SQL
Classifier: Topic :: Utilities
Classifier: Topic :: Software Development :: Quality Assurance
License-File: LICENSE
Requires-Dist: pandas
Requires-Dist: sqlfluff
Provides-Extra: dev
Requires-Dist: pre-commit; extra == "dev"
Requires-Dist: pandas-stubs; extra == "dev"
Requires-Dist: sphinx; extra == "dev"
Requires-Dist: pydata-sphinx-theme; extra == "dev"
Dynamic: license-file
